simple_8bit_cpu/alu.v
`timescale 1ns/1ps

module alu (
input [2:0] opcode,
input [7:0] operand1,
input [7:0] operand2,
output reg [7:0] result,
output reg zero_flag
);
always @(*) begin
case (opcode)
3'b000: result = operand1 + operand2; // ADD
3'b001: result = operand1 * operand2; // MUL
3'b010: result = operand1 & operand2; // AND
3'b011: result = operand1 | operand2; // OR
3'b100: result = operand1 ^ operand2; // XOR
3'b101: result = operand2; // MOV / JMP (forwarded)
3'b110: result = operand1 - operand2; // CMP (used internally for flags)
3'b111: result = ~operand1; // NOT
default: result = 8'b00000000;
endcase
// Zero flag set if result == 0
zero_flag = (result == 0) ? 1'b1 : 1'b0;
end
endmodule

simple_8bit_cpu/register_file.v
`timescale 1ns/1ps

module register_file (
    input clk,
    input write_en,
    input [2:0] write_addr,
    input [7:0] write_data,
    input [2:0] read_addr1,
    input [2:0] read_addr2,
    output [7:0] read_data1,
    output [7:0] read_data2
);

// Only 4 general-purpose registers physically used: R0 to R3
reg [7:0] registers [3:0];

// Masked addresses
wire [1:0] actual_write_addr = write_addr[1:0];
wire [1:0] actual_read_addr1 = read_addr1[1:0];
wire [1:0] actual_read_addr2 = read_addr2[1:0];

// Combinational read with write forwarding
assign read_data1 = (write_en && (actual_write_addr == actual_read_addr1)) ? write_data : registers[actual_read_addr1];
assign read_data2 = (write_en && (actual_write_addr == actual_read_addr2)) ? write_data : registers[actual_read_addr2];

// Sequential write
always @(posedge clk) begin
    if (write_en) begin
        registers[actual_write_addr] <= write_data;
        $display("REG WRITE: R[%0d] = %h", write_addr, write_data);
    end
end

endmodule

simple_8bit_cpu/instruction_decoder.v
`timescale 1ns/1ps

module instruction_decoder (
    input [7:0] instruction,
    output [2:0] opcode,
    output [2:0] reg1,
    output [2:0] reg2_or_imm
);

assign opcode        = instruction[7:5];
assign reg1          = {1'b0, instruction[4:3]};     // Destination (pad to 3 bits)
assign reg2_or_imm   = instruction[2:0];     // Source register or immediate (3 bits)

endmodule

simple_8bit_cpu/instruction_memory.v
`timescale 1ns/1ps

module instruction_memory (
    input [3:0] addr,
    output [7:0] data
);
    reg [7:0] memory [0:15];
    assign data = memory[addr];

    initial begin
        memory[ 0] = 8'hA6; // MOV R0, #2
        memory[ 1] = 8'hAF; // MOV R1, #3
        memory[ 2] = 8'hB4; // MOV R2, #0
        memory[ 3] = 8'hBD; // MOV R3, #1
        memory[ 4] = 8'h10; // ADD R2, R0
        memory[ 5] = 8'h31; // MUL R2, R1
        memory[ 6] = 8'h41; // AND R0, R1
        memory[ 7] = 8'h61; // OR R0, R1
        memory[ 8] = 8'h88; // XOR R1, R0
        memory[ 9] = 8'hF8; // NOT R3
        memory[10] = 8'hCB; // CMP R1, R3
        memory[11] = 8'h9B; // JZ 3
        memory[12] = 8'hA7; // MOV R0, #3
        memory[13] = 8'h7B; // JMP 3
        memory[14] = 8'h00; // NOP
        memory[15] = 8'h00; // NOP
    end
endmodule

simple_8bit_cpu/program_counter.v
`timescale 1ns/1ps

module program_counter (
    input clk,
    input reset,
    input jump,
    input [3:0] jump_addr,
    output reg [3:0] pc_out
);

always @(posedge clk or posedge reset) begin
    if (reset)
        pc_out <= 4'b0000;
    else if (jump)
        pc_out <= jump_addr;
    else
        pc_out <= pc_out + 1;
end

endmodule

simple_8bit_cpu/cpu.v
`timescale 1ns/1ps

module simple_cpu (
    input clk,
    input reset,
    output [3:0] pc
);

// Signals
wire [7:0] instruction;
wire [2:0] opcode;
wire [2:0] dest;
wire [2:0] src;
wire [7:0] reg_data1, reg_data2;
wire [7:0] alu_result;
wire zero_flag;

reg write_en;
reg [7:0] write_data;
reg [2:0] write_addr;
reg jump;
reg [3:0] jump_addr;

// Instantiate Program Counter
program_counter PC (
    .clk(clk),
    .reset(reset),
    .jump(jump),
    .jump_addr(jump_addr),
    .pc_out(pc)
);

// Instruction Memory
instruction_memory ROM (
    .addr(pc),
    .data(instruction)
);

// Decoder
instruction_decoder DEC (
    .instruction(instruction),
    .opcode(opcode),
    .reg1(dest),
    .reg2_or_imm(src)
);

// Register File (with address masking internally)
register_file REGFILE (
    .clk(clk),
    .write_en(write_en),
    .write_addr(write_addr),
    .write_data(write_data),
    .read_addr1(dest), // First operand comes from dest register for all ALU ops
    .read_addr2(src),  // Second operand comes from src register
    .read_data1(reg_data1),
    .read_data2(reg_data2)
);

// ALU
alu ALU (
    .operand1(reg_data1),
    .operand2(reg_data2),
    .opcode(opcode),
    .result(alu_result),
    .zero_flag(zero_flag)
);

// Execution Logic
always @(posedge clk) begin
    if (reset) begin
        write_en <= 0;
        jump <= 0;
        jump_addr <= 4'b0;
    end else begin
        write_en <= 0;
        write_addr <= dest;
        write_data <= 8'b0;
        jump <= 0;
        jump_addr <= 4'b0;

        case (opcode)

        3'b000: begin // ADD
            write_en <= 1;
            write_data <= alu_result;
            $display("ADD Executed: R1=%h, R2=%h, RESULT=%h, write_en=%b", reg_data1, reg_data2, alu_result, 1'b1);
            $display("CPU Cycle - PC=%d, Instruction=%h, Opcode=%b, Dest=%b, Src=%b", pc, instruction, opcode, dest, src);
        end

        3'b001: begin // MUL
            write_en <= 1;
            write_data <= alu_result;
            $display("MUL Executed: R%d = R%d * R%d = %h", dest, dest, src, alu_result);
        end

        3'b010: begin // AND
            write_en <= 1;
            write_data <= alu_result;
            $display("AND Executed: R%d = R%d & R%d = %h", dest, dest, src, alu_result);
        end

        3'b011: begin // OR
            write_en <= 1;
            write_data <= alu_result;
            $display("OR Executed: R%d = R%d | R%d = %h", dest, dest, src, alu_result);
        end

        3'b100: begin // XOR
            write_en <= 1;
            write_data <= alu_result;
            $display("XOR Executed: R%d = R%d ^ R%d = %h", dest, dest, src, alu_result);
        end

        3'b101: begin // MOV
            if (src[2] == 1'b1) begin
                // MOV immediate: upper src values (R4–R7) → signal imm
                write_addr <= dest;  // write to actual dest register
                write_en <= 1;
                write_data <= {5'b00000, src[1:0]};  // zero-extend the 2-bit immediate value
                $display("MOV IMM: R%d = #%h", dest, {5'b00000, src[1:0]});
            end else begin
                // MOV register to register
                write_en <= 1;
                write_data <= reg_data2;
                $display("MOV REG: R%d = R%d = %h", dest, src, reg_data2);
            end
        end

        3'b110: begin // CMP
            // only sets zero_flag
            write_en <= 0;
            $display("CMP Executed: R%d - R%d, zero_flag=%b", dest, src, zero_flag);
        end

        3'b111: begin // COM (bitwise NOT)
            write_en <= 1;
            write_data <= alu_result;
            $display("COM Executed: R%d = ~R%d = %h", dest, dest, alu_result);
        end

        endcase

        // Handle special jumps
        if (opcode == 3'b011 && dest == 3'b011) begin // JMP
            jump <= 1;
            jump_addr <= src;
            write_en <= 0;
            $display("JMP to address %d", src);
        end 
        else if (opcode == 3'b100 && dest == 3'b011) begin // JZ
            if (zero_flag) begin
                jump <= 1;
                jump_addr <= src;
                write_en <= 0;
                $display("JZ to address %d (zero_flag=1)", src);
            end else begin
                $display("JZ not taken (zero_flag=0)");
            end
        end 
        else if (opcode == 3'b101 && dest == 3'b011) begin // JNZ
            if (!zero_flag) begin
                jump <= 1;
                jump_addr <= src;
                write_en <= 0;
                $display("JNZ to address %d (zero_flag=0)", src);
            end else begin
                $display("JNZ not taken (zero_flag=1)");
            end
        end
    end
end

endmodule

simple_8bit_cpu/cpu_testbench.v
`timescale 1ns/1ps

module cpu_testbench();

    reg clk = 0;
    reg reset = 1;

    // Clock generation: 10ns period
    always #5 clk = ~clk;

    // Instantiate the CPU
    simple_cpu cpu (
        .clk(clk),
        .reset(reset)
    );

    // Create a wire to access internal pc_out from program_counter
    wire [3:0] pc;

    // Connect testbench wire to internal pc_out
    assign pc = cpu.PC.pc_out;

    initial begin
        // Generate VCD file for GTKWave
        $dumpfile("cpu.vcd");
        $dumpvars(0, cpu_testbench);

        // Initial reset pulse
        #10 reset = 0;

        // Let CPU run longer to complete all instructions
        #150;

        // Display final state
        $display("Final PC = %h", pc);
        $display("R0 = %h", cpu.REGFILE.registers[0]);
        $display("R1 = %h", cpu.REGFILE.registers[1]);
        $display("R2 = %h", cpu.REGFILE.registers[2]);
        $display("R3 = %h", cpu.REGFILE.registers[3]);

        $finish;
    end

endmodule

simple_8bit_cpu/cpu.vcd
$date
	Wed Jul 16 20:10:50 2025
$end
$version
	Icarus Verilog
$end
$timescale
	1ps
$end
$scope module cpu_testbench $end
$var wire 4 ! pc [3:0] $end
$var reg 1 " clk $end
$var reg 1 # reset $end
$scope module cpu $end
$var wire 1 " clk $end
$var wire 1 # reset $end
$var wire 1 $ zero_flag $end
$var wire 3 % src [2:0] $end
$var wire 8 & reg_data2 [7:0] $end
$var wire 8 ' reg_data1 [7:0] $end
$var wire 4 ( pc [3:0] $end
$var wire 3 ) opcode [2:0] $end
$var wire 8 * instruction [7:0] $end
$var wire 3 + dest [2:0] $end
$var wire 8 , alu_result [7:0] $end
$var reg 1 - jump $end
$var reg 4 . jump_addr [3:0] $end
$var reg 3 / write_addr [2:0] $end
$var reg 8 0 write_data [7:0] $end
$var reg 1 1 write_en $end
$scope module ALU $end
$var wire 8 2 operand2 [7:0] $end
$var wire 8 3 operand1 [7:0] $end
$var wire 3 4 opcode [2:0] $end
$var reg 8 5 result [7:0] $end
$var reg 1 $ zero_flag $end
$upscope $end
$scope module DEC $end
$var wire 3 6 reg2_or_imm [2:0] $end
$var wire 3 7 reg1 [2:0] $end
$var wire 3 8 opcode [2:0] $end
$var wire 8 9 instruction [7:0] $end
$upscope $end
$scope module PC $end
$var wire 1 " clk $end
$var wire 1 - jump $end
$var wire 4 : jump_addr [3:0] $end
$var wire 1 # reset $end
$var reg 4 ; pc_out [3:0] $end
$upscope $end
$scope module REGFILE $end
$var wire 1 " clk $end
$var wire 3 < read_addr1 [2:0] $end
$var wire 3 = read_addr2 [2:0] $end
$var wire 8 > read_data1 [7:0] $end
$var wire 8 ? read_data2 [7:0] $end
$var wire 3 @ write_addr [2:0] $end
$var wire 8 A write_data [7:0] $end
$var wire 1 1 write_en $end
$var wire 2 B actual_write_addr [1:0] $end
$var wire 2 C actual_read_addr2 [1:0] $end
$var wire 2 D actual_read_addr1 [1:0] $end
$upscope $end
$scope module ROM $end
$var wire 4 E addr [3:0] $end
$var wire 8 F data [7:0] $end
$upscope $end
$upscope $end
$upscope $end
$enddefinitions $end
$comment Show the parameter values. $end
$dumpall
$end
#0
$dumpvars
b10101101 F
b0 E
b1 D
b1 C
bx B
bx A
bx @
bx ?
bx >
b101 =
b1 <
b0 ;
bx :
b10101101 9
b101 8
b1 7
b101 6
bx 5
b101 4
bx 3
bx 2
x1
bx 0
bx /
bx .
x-
bx ,
b1 +
b10101101 *
b101 )
b0 (
bx '
bx &
b101 %
x$
1#
0"
b0 !
$end
#5000
b0 .
b0 :
0-
01
1"
#10000
0"
0#
#15000
b10 C
b10 D
b110 %
b110 6
b110 =
b10 +
b10 7
b10 <
b1 B
b10110110 *
b10110110 9
b10110110 F
b1 !
b1 (
b1 ;
b1 E
11
b1 0
b1 A
b1 /
b1 @
1"
#20000
0"
#25000
b11 C
b0 D
b111 %
b111 6
b111 =
b0 +
b0 7
b0 <
b110 )
b110 4
b110 8
b10 B
b11000111 *
b11000111 9
b11000111 F
b10 !
b10 (
b10 ;
b10 E
b10 0
b10 A
b10 /
b10 @
11
1"
#30000
0"
#35000
0$
b11 ,
b11 5
b10 &
b10 2
b10 ?
b10 C
b1 '
b1 3
b1 >
b1 D
b10 %
b10 6
b10 =
b1 +
b1 7
b1 <
b0 )
b0 4
b0 8
b0 B
b1010 *
b1010 9
b1010 F
b11 !
b11 (
b11 ;
b11 E
b0 0
b0 A
b0 /
b0 @
01
1"
#40000
0"
#45000
b10 '
b10 3
b10 >
b10 D
b100 ,
b100 5
b10 +
b10 7
b10 <
b1 )
b1 4
b1 8
b1 B
b110010 *
b110010 9
b110010 F
b100 !
b100 (
b100 ;
b100 E
b11 0
b11 A
11
b1 /
b1 @
1"
#50000
0"
#55000
x$
bx &
bx 2
bx ?
b11 C
b11 '
b11 3
b11 >
b1 D
b0xx ,
b0xx 5
b11 %
b11 6
b11 =
b1 +
b1 7
b1 <
b10 )
b10 4
b10 8
b10 B
b1001011 *
b1001011 9
b1001011 F
b101 !
b101 (
b101 ;
b101 E
b100 0
b100 A
b10 /
b10 @
11
1"
#60000
0"
#65000
0$
bx11 ,
bx11 5
b11 )
b11 4
b11 8
b1 B
b1101011 *
b1101011 9
b1101011 F
b110 !
b110 (
b110 ;
b110 E
b0xx 0
b0xx A
b1 /
b1 @
11
1"
#70000
0"
#75000
b11 D
b111 %
b111 6
b111 =
b11 +
b11 7
b11 <
x$
bx ,
bx 5
b1111111 *
b1111111 9
b1111111 F
b111 !
b111 (
b111 ;
b111 E
bx11 0
bx11 A
11
bx '
bx 3
bx >
1"
#80000
0"
#85000
bx11 '
bx11 3
bx11 >
b1 D
b11 %
b11 6
b11 =
b1 +
b1 7
b1 <
b100 )
b100 4
b100 8
b11 B
b10001011 *
b10001011 9
b10001011 F
b1000 !
b1000 (
b1000 ;
b1000 E
b111 .
b111 :
1-
bx 0
bx A
b11 /
b11 @
01
1"
#90000
0"
#95000
bx '
bx 3
bx >
b11 D
x$
bx ,
bx 5
b111 %
b111 6
b111 =
b11 +
b11 7
b11 <
b11 )
b11 4
b11 8
b1 B
b1111111 *
b1111111 9
b1111111 F
b111 !
b111 (
b111 ;
b111 E
11
b0 .
b0 :
0-
bx 0
bx A
b1 /
b1 @
1"
#100000
0"
#105000
b1 D
b11 %
b11 6
b11 =
b1 +
b1 7
b1 <
b100 )
b100 4
b100 8
b11 B
b10001011 *
b10001011 9
b10001011 F
b1000 !
b1000 (
b1000 ;
b1000 E
b111 .
b111 :
1-
bx 0
bx A
b11 /
b11 @
01
1"
#110000
0"
#115000
b11 D
b111 %
b111 6
b111 =
b11 +
b11 7
b11 <
b11 )
b11 4
b11 8
b1 B
b1111111 *
b1111111 9
b1111111 F
b111 !
b111 (
b111 ;
b111 E
11
b0 .
b0 :
0-
bx 0
bx A
b1 /
b1 @
1"
#120000
0"
#125000
b1 D
b11 %
b11 6
b11 =
b1 +
b1 7
b1 <
b100 )
b100 4
b100 8
b11 B
b10001011 *
b10001011 9
b10001011 F
b1000 !
b1000 (
b1000 ;
b1000 E
b111 .
b111 :
1-
bx 0
bx A
b11 /
b11 @
01
1"
#130000
0"
#135000
b11 D
b111 %
b111 6
b111 =
b11 +
b11 7
b11 <
b11 )
b11 4
b11 8
b1 B
b1111111 *
b1111111 9
b1111111 F
b111 !
b111 (
b111 ;
b111 E
11
b0 .
b0 :
0-
bx 0
bx A
b1 /
b1 @
1"
#140000
0"
#145000
b1 D
b11 %
b11 6
b11 =
b1 +
b1 7
b1 <
b100 )
b100 4
b100 8
b11 B
b10001011 *
b10001011 9
b10001011 F
b1000 !
b1000 (
b1000 ;
b1000 E
b111 .
b111 :
1-
bx 0
bx A
b11 /
b11 @
01
1"
#150000
0"
#155000
b11 D
b111 %
b111 6
b111 =
b11 +
b11 7
b11 <
b11 )
b11 4
b11 8
b1 B
b1111111 *
b1111111 9
b1111111 F
b111 !
b111 (
b111 ;
b111 E
11
b0 .
b0 :
0-
bx 0
bx A
b1 /
b1 @
1"
